dynhost
dynhost.service
setup.py
DynHost.egg-info/PKG-INFO
DynHost.egg-info/SOURCES.txt
DynHost.egg-info/dependency_links.txt
DynHost.egg-info/requires.txt
DynHost.egg-info/top_level.txt
dynhost_lib/__init__.py